reflect/__init__.py
reflect/parameter.py
reflect/token.py
reflect/version.py
reflect-0.3.0.dist-info/DESCRIPTION.rst
reflect-0.3.0.dist-info/METADATA
reflect-0.3.0.dist-info/RECORD
reflect-0.3.0.dist-info/WHEEL
reflect-0.3.0.dist-info/metadata.json
reflect-0.3.0.dist-info/top_level.txt
